[
  {
    "id": "gluttony",
    "displayName": "Gluttony",
    "description": "Needs twice as much food to feel full. Nutrient absorption is unaffected.",
    "category": "physical",
    "tags": ["food", "need"]
  },
  {
    "id": "runner",
    "displayName": "Runner",
    "description": "Moves faster than other dwarves.",
    "category": "physical",
    "tags": ["movement", "speed"]
  },
  {
    "id": "fit",
    "displayName": "Fit",
    "description": "Needs half as much food to feel full. Nutrient absorption is doubled.",
    "category": "physical",
    "tags": ["food", "need", "nutrition"]
  },
  {
    "id": "lazy",
    "displayName": "Lazy",
    "description": "Moves slower when performing tasks related to disliked things.",
    "category": "mental",
    "tags": ["movement", "work"]
  },
  {
    "id": "motivated",
    "displayName": "Motivated",
    "description": "Moves faster when performing tasks related to liked things.",
    "category": "mental",
    "tags": ["movement", "work"]
  },
  {
    "id": "fearful",
    "displayName": "Fearful",
    "description": "Might flee and stay away from animals when they get too close.",
    "category": "mental",
    "tags": ["fear", "animal"]
  },
  {
    "id": "fears_water",
    "displayName": "Fears Water",
    "description": "Will not go near water tiles. Refuses jobs that require proximity to water.",
    "category": "phobia",
    "tags": ["fear", "water", "job_refusal"]
  },
  {
    "id": "sleepy",
    "displayName": "Sleepy",
    "description": "Sleep need increases double as fast. Always tired.",
    "category": "physical",
    "tags": ["sleep", "need"]
  },
  {
    "id": "energetic",
    "displayName": "Energetic",
    "description": "Sleep decreases (recovers) double as fast. Wakes up refreshed quickly.",
    "category": "physical",
    "tags": ["sleep", "need"]
  },
  {
    "id": "strong",
    "displayName": "Strong",
    "description": "Can carry 50% more weight than other dwarves.",
    "category": "physical",
    "tags": ["carry", "strength"]
  }
]
